README.rst
setup.py
racks/__init__.py
racks/main.py
racks.egg-info/PKG-INFO
racks.egg-info/SOURCES.txt
racks.egg-info/dependency_links.txt
racks.egg-info/entry_points.txt
racks.egg-info/requires.txt
racks.egg-info/top_level.txt