Metadata-Version: 1.0
Name: racks
Version: 1.0.0
Summary: racks for stack graphs
Home-page: http://www.github.com/myusuf3/racks
Author: Mahdi Yusuf
Author-email: yusuf.mahdi@gmail.com
License: MIT License
Platform: UNKNOWN
Classifier: Development Status :: 4 - Beta
Classifier: Intended Audience :: Developers
Classifier: Natural Language :: English
Classifier: License :: OSI Approved :: MIT License
Classifier: Programming Language :: Python
Classifier: Programming Language :: Python :: 2.6
Classifier: Programming Language :: Python :: 2.7
